easyted/__init__.py
easyted/ted.py
easyted-0.0.3.dist-info/LICENSE
easyted-0.0.3.dist-info/METADATA
easyted-0.0.3.dist-info/WHEEL
easyted-0.0.3.dist-info/top_level.txt
easyted-0.0.3.dist-info/RECORD
