Metadata-Version: 2.1
Name: easyted
Version: 0.0.3
Summary: A Python library for easy calculation of tree edit distances with visualization capabilities.
Home-page: https://github.com/LasalJayawardena/easyted
Author: Lasal Jayawardena
Author-email: lasalcjl@gmail.com
Classifier: Programming Language :: Python :: 3
Classifier: License :: OSI Approved :: MIT License
Classifier: Operating System :: OS Independent
Requires-Python: >=3.6
License-File: LICENSE
Requires-Dist: nltk >=3.5
Requires-Dist: stanza >=1.2
Requires-Dist: apted >=1.0
